LICENSE
README.md
setup.cfg
setup.py
pyassist_utils/CustomError.py
pyassist_utils/__init__.py
pyassist_utils/process.py
pyassist_utils/utils.py
pyassist_utils.egg-info/PKG-INFO
pyassist_utils.egg-info/SOURCES.txt
pyassist_utils.egg-info/dependency_links.txt
pyassist_utils.egg-info/requires.txt
pyassist_utils.egg-info/top_level.txt